{
    "country": "US",
    "current_r": 0.7964688641655637,
    "date": "2020-06-23",
    "first_date": "2020-02-17",
    "fixed_params": [
        [
            "PROJECTION_END_DATE",
            "2020-10-01"
        ],
        [
            "INCUBATION_DAYS",
            2
        ],
        [
            "INFECTIOUS_DAYS_ARR",
            [
                0.5,
                1.0,
                2.0,
                3.0,
                2.0,
                1.0,
                0.5
            ]
        ],
        [
            "DEATHS_DAYS_ARR",
            [
                1,
                1,
                1,
                1,
                1,
                1,
                1,
                1,
                1,
                1,
                1,
                1,
                1,
                1,
                1
            ]
        ],
        [
            "DAYS_UNTIL_HOSPITALIZATION",
            12
        ],
        [
            "HOSPITALIZATION_RATE",
            0.03
        ],
        [
            "DAYS_IN_HOSPITAL",
            11
        ],
        [
            "DAYS_BEFORE_DEATH",
            22
        ],
        [
            "MEAN_ERROR_DECAY",
            1
        ],
        [
            "MEAN_ERROR_DECAY_LOWER",
            0.95
        ],
        [
            "MIN_ALPHA_RATIO",
            0.1
        ],
        [
            "LOSS_FUNCTION_NAME",
            "nth_power_diff"
        ],
        [
            "NTH_POWER_ERROR",
            2
        ],
        [
            "MODEL_WEIGHT_ERROR_POWER",
            1.5
        ],
        [
            "PERC_PARAMS_PER_INFECTION_DAY",
            0.075
        ],
        [
            "PERC_PARAMS_PER_INFECTION_DAY_US_EUROPE",
            0.075
        ],
        [
            "MIN_PARAMS_PER_INFLECTION_DAY",
            20
        ],
        [
            "DAYS_UNTIL_RECOVERY",
            15
        ],
        [
            "IMMUNITY_MULTIPLIER",
            0.5
        ],
        [
            "IMMUNITY_MULTIPLIER_US_SUBREGION",
            0.25
        ],
        [
            "PREV_WEEK_RATIO_SENSITIVITY",
            0.75
        ],
        [
            "DAYS_UNTIL_LOCKDOWN_FATIGUE",
            28
        ],
        [
            "MAX_POST_REOPEN_R",
            1.16
        ],
        [
            "MORTALITY_MULTIPLIER",
            0.995
        ],
        [
            "MIN_MORTALITY_MULTIPLIER",
            0.5
        ],
        [
            "DAYS_WITH_IMPORTS",
            100
        ],
        [
            "USE_UNDETECTED_DEATHS_RATIO",
            true
        ],
        [
            "DEFAULT_REOPEN_SHIFT_DAYS",
            15
        ]
    ],
    "mean_params": [
        [
            "INITIAL_R_0",
            5.334849954746788
        ],
        [
            "LOCKDOWN_R_0",
            0.8113173831971048
        ],
        [
            "INFLECTION_DAY",
            "2020-03-09"
        ],
        [
            "RATE_OF_INFLECTION",
            0.38327183956056216
        ],
        [
            "LOCKDOWN_FATIGUE",
            1.0
        ],
        [
            "DAILY_IMPORTS",
            391.3175679435438
        ],
        [
            "MORTALITY_RATE",
            0.012500000000000002
        ],
        [
            "REOPEN_DATE",
            "2020-06-15"
        ],
        [
            "REOPEN_SHIFT_DAYS",
            0.0
        ],
        [
            "REOPEN_R_MULT",
            1.304097362090679
        ],
        [
            "POST_REOPENING_R_DECAY",
            0.9973575414787011
        ]
    ],
    "median_params": [
        [
            "INITIAL_R_0",
            5.2
        ],
        [
            "LOCKDOWN_R_0",
            0.7500000000000001
        ],
        [
            "INFLECTION_DAY",
            "2020-03-10"
        ],
        [
            "RATE_OF_INFLECTION",
            0.5
        ],
        [
            "LOCKDOWN_FATIGUE",
            1.0
        ],
        [
            "DAILY_IMPORTS",
            300.0
        ],
        [
            "MORTALITY_RATE",
            0.0125
        ],
        [
            "REOPEN_DATE",
            "2020-06-15"
        ],
        [
            "REOPEN_SHIFT_DAYS",
            0.0
        ],
        [
            "REOPEN_R_MULT",
            1.4
        ],
        [
            "POST_REOPENING_R_DECAY",
            0.9974188979332765
        ]
    ],
    "num_params": 4320,
    "num_params_filt": 234,
    "population": 8336817,
    "projection_end_date": "2020-10-01",
    "region": "NY",
    "subregion": "New York City",
    "top10_params": [
        [
            "INITIAL_R_0",
            5.359999999999999
        ],
        [
            "LOCKDOWN_R_0",
            0.81
        ],
        [
            "INFLECTION_DAY",
            "2020-03-08"
        ],
        [
            "RATE_OF_INFLECTION",
            0.33999999999999997
        ],
        [
            "LOCKDOWN_FATIGUE",
            1.0
        ],
        [
            "DAILY_IMPORTS",
            420.0
        ],
        [
            "MORTALITY_RATE",
            0.012500000000000004
        ],
        [
            "REOPEN_DATE",
            "2020-06-15"
        ],
        [
            "REOPEN_SHIFT_DAYS",
            0.0
        ],
        [
            "REOPEN_R_MULT",
            1.3399999999999999
        ],
        [
            "POST_REOPENING_R_DECAY",
            0.997440160406361
        ]
    ],
    "top_params": [
        [
            "INITIAL_R_0",
            5.2
        ],
        [
            "LOCKDOWN_R_0",
            0.8000000000000002
        ],
        [
            "INFLECTION_DAY",
            "2020-03-08"
        ],
        [
            "RATE_OF_INFLECTION",
            0.3
        ],
        [
            "LOCKDOWN_FATIGUE",
            1.0
        ],
        [
            "DAILY_IMPORTS",
            500
        ],
        [
            "MORTALITY_RATE",
            0.0125
        ],
        [
            "REOPEN_DATE",
            "2020-06-15"
        ],
        [
            "REOPEN_SHIFT_DAYS",
            0
        ],
        [
            "REOPEN_R_MULT",
            1.5999999999999999
        ],
        [
            "POST_REOPENING_R_DECAY",
            0.9986256915333988
        ]
    ]
}