{
    "country": "Germany",
    "current_r": 0.8868617697544318,
    "date": "2020-07-19",
    "first_date": "2020-02-14",
    "fixed_params": [
        [
            "PROJECTION_END_DATE",
            "2020-11-01"
        ],
        [
            "INCUBATION_DAYS",
            2
        ],
        [
            "INFECTIOUS_DAYS_ARR",
            [
                0.5,
                1.0,
                2.0,
                3.0,
                2.0,
                1.0,
                0.5
            ]
        ],
        [
            "DEATHS_DAYS_ARR",
            [
                1,
                1,
                1,
                1,
                1,
                1,
                1,
                1,
                1,
                1,
                1,
                1,
                1,
                1,
                1
            ]
        ],
        [
            "DAYS_UNTIL_HOSPITALIZATION",
            12
        ],
        [
            "HOSPITALIZATION_RATE",
            0.034
        ],
        [
            "DAYS_IN_HOSPITAL",
            11
        ],
        [
            "DAYS_BEFORE_DEATH",
            22
        ],
        [
            "MEAN_ERROR_DECAY",
            1
        ],
        [
            "MEAN_ERROR_DECAY_LOWER",
            0.95
        ],
        [
            "MIN_ALPHA_RATIO",
            0.1
        ],
        [
            "LOSS_FUNCTION_NAME",
            "nth_power_diff"
        ],
        [
            "NTH_POWER_ERROR",
            2
        ],
        [
            "MODEL_WEIGHT_ERROR_POWER",
            1.5
        ],
        [
            "PERC_PARAMS_PER_INFECTION_DAY",
            0.075
        ],
        [
            "PERC_PARAMS_PER_INFECTION_DAY_US_EUROPE",
            0.075
        ],
        [
            "MIN_PARAMS_PER_INFLECTION_DAY",
            20
        ],
        [
            "DAYS_UNTIL_RECOVERY",
            15
        ],
        [
            "IMMUNITY_MULTIPLIER",
            0.5
        ],
        [
            "IMMUNITY_MULTIPLIER_US_SUBREGION",
            0.3
        ],
        [
            "PREV_WEEK_RATIO_SENSITIVITY",
            0.75
        ],
        [
            "DAYS_UNTIL_LOCKDOWN_FATIGUE",
            28
        ],
        [
            "MAX_POST_REOPEN_R",
            1.2
        ],
        [
            "MORTALITY_MULTIPLIER",
            0.995
        ],
        [
            "MORTALITY_MULTIPLIER_US_REOPEN",
            0.98
        ],
        [
            "MIN_MORTALITY_MULTIPLIER",
            0.3
        ],
        [
            "MIN_IFR",
            0.0025
        ],
        [
            "DAYS_WITH_IMPORTS",
            100
        ],
        [
            "USE_UNDETECTED_DEATHS_RATIO",
            true
        ],
        [
            "DEFAULT_REOPEN_SHIFT_DAYS",
            15
        ],
        [
            "RANDOMIZED_PARAMS",
            [
                "POST_REOPENING_R_DECAY",
                "FALL_R_MULTIPLIER",
                "POST_REOPENING_EQUILIBRIUM_R"
            ]
        ]
    ],
    "mean_params": [
        [
            "INITIAL_R_0",
            2.2394212578049046
        ],
        [
            "LOCKDOWN_R_0",
            0.8150390379195401
        ],
        [
            "INFLECTION_DAY",
            "2020-03-18"
        ],
        [
            "RATE_OF_INFLECTION",
            0.39242414501684675
        ],
        [
            "LOCKDOWN_FATIGUE",
            1.0
        ],
        [
            "DAILY_IMPORTS",
            532.7031078996966
        ],
        [
            "MORTALITY_RATE",
            0.007500000000000001
        ],
        [
            "REOPEN_DATE",
            "2020-05-15"
        ],
        [
            "REOPEN_SHIFT_DAYS",
            7.000000000000001
        ],
        [
            "REOPEN_R_MULT",
            1.0786694423939793
        ],
        [
            "POST_REOPENING_R_DECAY",
            0.996183565128171
        ],
        [
            "FALL_R_MULTIPLIER",
            1.0013847162877834
        ],
        [
            "POST_REOPENING_EQUILIBRIUM_R",
            1.0004713294235397
        ]
    ],
    "median_params": [
        [
            "INITIAL_R_0",
            2.4
        ],
        [
            "LOCKDOWN_R_0",
            0.8000000000000002
        ],
        [
            "INFLECTION_DAY",
            "2020-03-18"
        ],
        [
            "RATE_OF_INFLECTION",
            0.3
        ],
        [
            "LOCKDOWN_FATIGUE",
            1.0
        ],
        [
            "DAILY_IMPORTS",
            500.0
        ],
        [
            "MORTALITY_RATE",
            0.0075
        ],
        [
            "REOPEN_DATE",
            "2020-05-15"
        ],
        [
            "REOPEN_SHIFT_DAYS",
            7.0
        ],
        [
            "REOPEN_R_MULT",
            1.1
        ],
        [
            "POST_REOPENING_R_DECAY",
            0.9961482259367513
        ],
        [
            "FALL_R_MULTIPLIER",
            1.0012663649412423
        ],
        [
            "POST_REOPENING_EQUILIBRIUM_R",
            1.0024588111891417
        ]
    ],
    "num_params": 6048,
    "num_params_filt": 456,
    "population": 83019213,
    "projection_end_date": "2020-11-01",
    "region": "ALL",
    "subregion": "",
    "top10_params": [
        [
            "INITIAL_R_0",
            2.18
        ],
        [
            "LOCKDOWN_R_0",
            0.8200000000000001
        ],
        [
            "INFLECTION_DAY",
            "2020-03-19"
        ],
        [
            "RATE_OF_INFLECTION",
            0.43999999999999995
        ],
        [
            "LOCKDOWN_FATIGUE",
            1.0
        ],
        [
            "DAILY_IMPORTS",
            475.0
        ],
        [
            "MORTALITY_RATE",
            0.0075
        ],
        [
            "REOPEN_DATE",
            "2020-05-15"
        ],
        [
            "REOPEN_SHIFT_DAYS",
            7.000000000000001
        ],
        [
            "REOPEN_R_MULT",
            1.07
        ],
        [
            "POST_REOPENING_R_DECAY",
            0.9966951976771682
        ],
        [
            "FALL_R_MULTIPLIER",
            1.0018718759166627
        ],
        [
            "POST_REOPENING_EQUILIBRIUM_R",
            1.0011624221047155
        ]
    ],
    "top_params": [
        [
            "INITIAL_R_0",
            2.5999999999999996
        ],
        [
            "LOCKDOWN_R_0",
            0.8000000000000002
        ],
        [
            "INFLECTION_DAY",
            "2020-03-17"
        ],
        [
            "RATE_OF_INFLECTION",
            0.3
        ],
        [
            "LOCKDOWN_FATIGUE",
            1.0
        ],
        [
            "DAILY_IMPORTS",
            250
        ],
        [
            "MORTALITY_RATE",
            0.0075
        ],
        [
            "REOPEN_DATE",
            "2020-05-15"
        ],
        [
            "REOPEN_SHIFT_DAYS",
            7
        ],
        [
            "REOPEN_R_MULT",
            1.1500000000000001
        ],
        [
            "POST_REOPENING_R_DECAY",
            0.996087234288455
        ],
        [
            "FALL_R_MULTIPLIER",
            1.0024120856207532
        ],
        [
            "POST_REOPENING_EQUILIBRIUM_R",
            1.0747599547045166
        ]
    ]
}